agitops/__init__.py
agitops/agent/__init__.py
agitops/agent/browser/__init__.py
agitops/agent/browser/__main__.py
agitops/agent/explorer/__init__.py
agitops/agent/explorer/__main__.py
agitops/agent/planner/__init__.py
agitops/agent/planner/__main__.py
agitops/tool/__init__.py
agitops/tool/bash.py
agitops/tool/browser.py
agitops/tool/google.py
agitops/util/__init__.py
agitops/util/command.py
agitops-0.0.50.dist-info/METADATA
agitops-0.0.50.dist-info/WHEEL
agitops-0.0.50.dist-info/top_level.txt
agitops-0.0.50.dist-info/RECORD
